polyads/__init__.py
polyads/binary_search.py
polyads/data.py
polyads/fitter.py
polyads/losses.py
polyads/model.py
polyads/polyad_eval.py
polyads/polyad_generation.py
polyads/polyad_utils.py
polyads/utils.py
polyads/validations.py
polyads-0.0.1.dist-info/METADATA
polyads-0.0.1.dist-info/WHEEL
polyads-0.0.1.dist-info/licenses/LICENSE
polyads-0.0.1.dist-info/RECORD
