Metadata-Version: 2.4
Name: polyads
Version: 0.0.1
Summary:  A Python package for estimating multi-way gravity models with high-dimensional fixed effects. The polyad estimator addresses the incidental parameter problem in Poisson models by conditioning on sufficient statistics for fixed effects. 
Project-URL: Homepage, https://lucasresenderc.github.io/
Author-email: Lucas Resende <lucasresenderc@gmail.com>
License:                     GNU AFFERO GENERAL PUBLIC LICENSE
License-File: LICENSE
Classifier: Operating System :: OS Independent
Classifier: Programming Language :: Python :: 3
Requires-Python: >=3.8
